bot_controller/__init__.py
bot_controller/bc_serial.py
bot_controller/controller.py
bot_controller/factory.py
bot_controller/joystick.py
bot_controller/keyboard.py
bot_controller/main.py
bot_controller/protocol.py
bot_controller/server.py
bot_controller-0.2.dist-info/METADATA
bot_controller-0.2.dist-info/WHEEL
bot_controller-0.2.dist-info/entry_points.txt
bot_controller-0.2.dist-info/licenses/LICENSE.txt
bot_controller-0.2.dist-info/RECORD
