Metadata-Version: 2.1
Name: bot-controller
Version: 0.2
Summary: Package to easily control your DotBot and Sail Boat with different controllers.
Project-URL: Homepage, https://github.com/DotBots/BotController-python
Project-URL: Bug Tracker, https://github.com/DotBots/BotController-python/issues
Author-email: Theo Akbas <theo.akbas@inria.fr>
License: Copyright 2022 Inria
Classifier: License :: OSI Approved :: MIT License
Classifier: Operating System :: OS Independent
Classifier: Programming Language :: Python :: 3
Requires-Python: >=3.7
Requires-Dist: bottle==0.12.21
Requires-Dist: pygame==2.1.2
Requires-Dist: pynput==1.7.6
Requires-Dist: pyserial==3.5
Requires-Dist: requests==2.28.1
